<?xml version='1.0' encoding='UTF-8'?>
<data>
  <tile>0,0,0,0,0,0,0,0,0|0,22,22,22,22,22,22,22,0|0,22,22,22,22,22,22,22,0|0,22,22,22,22,22,22,22,0|0,0,22,22,22,22,22,0,0|0,0,0,22,22,22,0,0,0|0,0,0,0,22,0,0,0,0|0,0,0,0,0,0,0,0,0|0,0,0,0,0,0,0,0,0</tile>
  <board>0,0,0,0,0,0,0,0,0|0,0,0,0,0,0,0,0,0|0,0,0,0,0,0,0,0,0|0,0,0,0,0,0,0,0,0|0,0,0,0,0,0,0,0,0|0,0,0,0,0,0,0,0,0|0,0,0,0,0,0,0,0,0|0,0,0,0,0,0,0,0,0|0,0,0,0,0,0,0,0,0</board>
  <candy>0,0,0,0,0,0,0,0,0|0,4,3,4,1,1,2,5,0|0,2,1,2,2,5,3,4,0|0,4,5,3,5,3,4,1,0|0,0,3,1,4,1,4,0,0|0,0,0,4,1,2,0,0,0|0,0,0,0,2,0,0,0,0|0,0,0,0,0,0,0,0,0|0,0,0,0,0,0,0,0,0</candy>
  <barrier>0,0,0,0,0,0,0,0,0|0,0,0,0,0,0,0,0,0|0,0,0,0,0,0,0,0,0|0,0,0,0,0,0,0,0,0|0,0,0,0,0,0,0,0,0|0,0,0,0,0,0,0,0,0|0,0,0,0,0,0,0,0,0|0,0,0,0,0,0,0,0,0|0,0,0,0,0,0,0,0,0</barrier>
  <entryAndExit>0,0,0,0,0,0,0,0,0|0,23,23,23,23,23,23,23,0|0,0,0,0,0,0,0,0,0|0,0,0,0,0,0,0,0,0|0,0,0,0,0,0,0,0,0|0,0,0,0,0,0,0,0,0|0,0,0,0,0,0,0,0,0|0,0,0,0,0,0,0,0,0|0,0,0,0,0,0,0,0,0</entryAndExit>
   <aim>1,10</aim>
   <mode>0</mode>
   <scoreAim>680</scoreAim>
   <step>17</step>
</data>